toolkit4nlp/__init__.py
toolkit4nlp/backend.py
toolkit4nlp/evaluation.py
toolkit4nlp/initializers.py
toolkit4nlp/layers.py
toolkit4nlp/models.py
toolkit4nlp/optimizers.py
toolkit4nlp/tokenizers.py
toolkit4nlp/utils.py
toolkit4nlp-0.5.0.dist-info/LICENSE
toolkit4nlp-0.5.0.dist-info/METADATA
toolkit4nlp-0.5.0.dist-info/WHEEL
toolkit4nlp-0.5.0.dist-info/top_level.txt
toolkit4nlp-0.5.0.dist-info/RECORD
