Metadata-Version: 2.1
Name: toolkit4nlp
Version: 0.5.0
Summary: an toolkit for nlp research
Home-page: https://github.com/xv44586/toolkit4nlp
Author: xv44586
Author-email: xv44586@gmail.com
License: Apache License 2.0
Platform: UNKNOWN
Requires-Dist: keras (<=2.3.1)
